{
  "ruleChain": {
    "additionalInfo": {
      "description": "power Esd"
    },
    "name": "TAS-SOP3-Power ESD",
    "firstRuleNodeId": null,
    "root": false,
    "debugMode": true,
    "configuration": null
  },
  "metadata": {
    "firstNodeIndex": 3,
    "nodes": [
      {
        "additionalInfo": {
          "description": "",
          "layoutX": 623,
          "layoutY": 285
        },
        "type": "org.thingsboard.rule.engine.action.TbCreateAlarmNode",
        "name": "Create Power ESD Alerm",
        "debugMode": true,
        "configuration": {
          "alarmDetailsBuildJs": "var details = {};\nif (metadata.prevAlarmDetails) {\n    details = JSON.parse(metadata.prevAlarmDetails);\n}\nvar msg_data = msg\nvar additionalinfo = JSON.parse(metadata[\"additionalInfo\"]);\ndetails[\"additionalInfo\"] = additionalinfo;\ndetails[\"additionalInfo\"][\"unitName\"] = metadata[\"device_name\"];\ndetails[\"additionalInfo\"][\"plantlocation\"] = metadata[\"ss_plantlocation\"];\ndetails[\"additionalInfo\"][\"interlock_name\"] = \"Plant Power ESD Shutdown\";\ndetails[\"additionalInfo\"][\"plantlocationid\"] = metadata[\"ss_plantlocationid\"];\ndetails[\"additionalInfo\"][\"device_id\"] = metadata[\"device_id\"];\ndetails[\"additionalInfo\"][\"sap_id\"] = metadata[\"ss_sap_id\"];\ndetails[\"additionalInfo\"][\"bu\"] = metadata[\"ss_bu\"];\ndetails[\"additionalInfo\"][\"sop_id\"] = \"SOP003\";\ndetails['additionalInfo']['deviceId'] = metadata['deviceId']\ndetails['additionalInfo']['deviceName'] = metadata['originatorName']\ndetails['additionalInfo']['deviceType'] = metadata[\"device_type\"]\ndetails['additionalInfo']['customData'] = msg_data\n\nreturn details;",
          "useMessageAlarmData": false,
          "alarmType": "PowerESD Alarm",
          "severity": "CRITICAL",
          "propagate": false,
          "relationTypes": []
        }
      },
      {
        "additionalInfo": {
          "description": "",
          "layoutX": 321,
          "layoutY": 315
        },
        "type": "org.thingsboard.rule.engine.filter.TbJsFilterNode",
        "name": "Power ESD Status Check",
        "debugMode": true,
        "configuration": {
          "jsScript": "if (msg[\"POWER SWITCH STATUS\"] != undefined && (msg[\"POWER SWITCH STATUS\"] != metadata[\"ss_POWER SWITCH STATUS\"])){\n    return true\n}\nreturn false"
        }
      },
      {
        "additionalInfo": {
          "description": "",
          "layoutX": 1132,
          "layoutY": 355
        },
        "type": "org.thingsboard.rule.engine.rabbitmq.TbRabbitMqNode",
        "name": "CEG Alert Publisher",
        "debugMode": true,
        "configuration": {
          "exchangeNamePattern": "",
          "routingKeyPattern": "ceg_tb_listener",
          "messageProperties": "PERSISTENT_BASIC",
          "host": "localhost",
          "port": 5672,
          "virtualHost": "/hpcl_ceg",
          "username": "hpcl_ceg",
          "password": "algo@4321",
          "automaticRecoveryEnabled": true,
          "connectionTimeout": 60000,
          "handshakeTimeout": 10000,
          "clientProperties": {}
        }
      },
      {
        "additionalInfo": {
          "description": "",
          "layoutX": 339,
          "layoutY": 157
        },
        "type": "org.thingsboard.rule.engine.metadata.TbGetOriginatorFieldsNode",
        "name": "Server Fields",
        "debugMode": true,
        "configuration": {
          "fieldsMapping": {
            "name": "originatorName",
            "type": "originatorType",
            "additionalInfo": "additionalInfo",
            "id": "deviceId",
            "tenantId": "tenantid"
          }
        }
      },
      {
        "additionalInfo": {
          "description": "",
          "layoutX": 571,
          "layoutY": 76
        },
        "type": "org.thingsboard.rule.engine.filter.TbJsFilterNode",
        "name": "Power Esd Check",
        "debugMode": true,
        "configuration": {
          "jsScript": "if (metadata[\"device_type\"] == \"Power Switch\"){\n    return true\n}\nreturn false"
        }
      },
      {
        "additionalInfo": {
          "description": "",
          "layoutX": 628,
          "layoutY": 378
        },
        "type": "org.thingsboard.rule.engine.action.TbClearAlarmNode",
        "name": "Clear Power ESD Alarm",
        "debugMode": true,
        "configuration": {
          "alarmDetailsBuildJs": "var details = {};\nif (metadata.prevAlarmDetails) {\n    details = JSON.parse(metadata.prevAlarmDetails);\n}\nvar additionalinfo = JSON.parse(metadata[\"additionalInfo\"]);\ndetails[\"additionalInfo\"] = additionalinfo;\ndetails[\"additionalInfo\"][\"unitName\"] = metadata[\"device_name\"];\ndetails[\"additionalInfo\"][\"interlock_name\"] = \"Plant Power ESD Shutdown\";\ndetails[\"additionalInfo\"][\"plantlocation\"] = metadata[\"ss_plantlocation\"];\ndetails[\"additionalInfo\"][\"plantlocationid\"] = metadata[\"ss_plantlocationid\"];\ndetails[\"additionalInfo\"][\"sap_id\"] = metadata[\"ss_sap_id\"];\ndetails[\"additionalInfo\"][\"bu\"] = metadata[\"ss_bu\"];\ndetails[\"additionalInfo\"][\"sop_id\"] = \"SOP003\";\nreturn details;",
          "alarmType": "PowerESD Alarm"
        }
      },
      {
        "additionalInfo": {
          "description": "",
          "layoutX": 806,
          "layoutY": 124
        },
        "type": "org.thingsboard.rule.engine.metadata.TbGetAttributesNode",
        "name": "Server Scope Attributes",
        "debugMode": true,
        "configuration": {
          "tellFailureIfAbsent": true,
          "clientAttributeNames": [],
          "sharedAttributeNames": [],
          "serverAttributeNames": [
            "bu",
            "plantlocation",
            "plantlocationid",
            "sap_id",
            "POWER SWITCH STATUS"
          ],
          "latestTsKeyNames": [],
          "getLatestValueWithTs": false
        }
      }
    ],
    "connections": [
      {
        "fromIndex": 0,
        "toIndex": 2,
        "type": "Created"
      },
      {
        "fromIndex": 1,
        "toIndex": 0,
        "type": "True"
      },
      {
        "fromIndex": 1,
        "toIndex": 5,
        "type": "False"
      },
      {
        "fromIndex": 3,
        "toIndex": 4,
        "type": "Success"
      },
      {
        "fromIndex": 4,
        "toIndex": 6,
        "type": "True"
      },
      {
        "fromIndex": 5,
        "toIndex": 2,
        "type": "Cleared"
      },
      {
        "fromIndex": 6,
        "toIndex": 1,
        "type": "Success"
      }
    ],
    "ruleChainConnections": null
  }
}